droid/__init__.py
droid/main.py
droid/view.py
droid-1.4.22.data/scripts/main.py
droid-1.4.22.dist-info/LICENSE
droid-1.4.22.dist-info/METADATA
droid-1.4.22.dist-info/WHEEL
droid-1.4.22.dist-info/entry_points.txt
droid-1.4.22.dist-info/top_level.txt
droid-1.4.22.dist-info/RECORD
