Metadata-Version: 2.1
Name: droid
Version: 1.4.22
Summary: Droid is a remote communication application created to communicate with Android devices on the local network over the Android debug bridge (adb). Available as a CLI or GUI.
Home-page: https://github.com/battleoverflow/droid
Author: battleoverflow
Classifier: Programming Language :: Python :: 3
Classifier: License :: OSI Approved :: MIT License
Classifier: Operating System :: OS Independent
Requires-Python: >=3.6
License-File: LICENSE
Requires-Dist: argparse
Requires-Dist: customtkinter ==4.6.3
